opml/__init__.py
opml/document.py
opml/exceptions.py
opml/outlinable.py
opml/outline.py
pyopml-1.0.0.dist-info/LICENSE.md
pyopml-1.0.0.dist-info/METADATA
pyopml-1.0.0.dist-info/WHEEL
pyopml-1.0.0.dist-info/top_level.txt
pyopml-1.0.0.dist-info/RECORD
