Metadata-Version: 2.1
Name: pyopml
Version: 1.0.0
Summary: Python package meant to read, manipulate and write OPML 2.0 files
Home-page: https://github.com/EpocDotFr/pyopml
Author: Maxime "Epoc" G.
Author-email: contact.nospam@epoc.nospam.fr
License: DBAD
Platform: UNKNOWN
Classifier: Development Status :: 5 - Production/Stable
Classifier: Intended Audience :: Developers
Classifier: Topic :: Software Development :: Libraries
Classifier: Operating System :: OS Independent
Classifier: Programming Language :: Python
Classifier: Programming Language :: Python :: 3.6
Classifier: Programming Language :: Python :: 3.7
Classifier: Programming Language :: Python :: 3.8
Classifier: Programming Language :: Python :: 3.9
Requires-Python: >=3.6.0
Requires-Dist: lxml (>=4.6)
Provides-Extra: dev
Requires-Dist: twine ; extra == 'dev'
Requires-Dist: Sphinx ; extra == 'dev'
Requires-Dist: pytest ; extra == 'dev'
